ADNI_Part/run_adni.py
ADNI_Part/utils_adni.py
bebms/__init__.py
bebms/cross_validate.py
bebms/generate_data.py
bebms/mallows_hamming.py
bebms/mallows_kendall.py
bebms/mallows_model.py
bebms/mh.py
bebms/permutil.py
bebms/run.py
bebms/utils.py
bebms/viz.py
bebms/data/__init__.py
bebms/test/gen.py
bebms/test/test.py
bebms/test/test_sustain.py
deprecated/for_chat.py
deprecated/gen copy.py
deprecated/generate_data copy.py
deprecated/mh copy 2.py
deprecated/mh copy.py
deprecated/mh_all_updates.py
deprecated/mh_known_theta_phi.py
deprecated/mh_with_labels_only.py
deprecated/mh_without_label_purely.py
deprecated/run copy 2.py
deprecated/run copy 3.py
deprecated/run copy.py
deprecated/run_with_labels_only.py
deprecated/run_without_label_purely.py
deprecated/test copy.py
deprecated/utils copy 2.py
deprecated/utils copy.py
deprecated/utils_with_labels_only.py
bebms-0.6.0.dist-info/LICENSE
bebms-0.6.0.dist-info/METADATA
bebms-0.6.0.dist-info/WHEEL
bebms-0.6.0.dist-info/top_level.txt
bebms-0.6.0.dist-info/RECORD
