Metadata-Version: 2.1
Name: bebms
Version: 0.6.0
Summary: Bayesian Event-Based Model for Disease Subtype and Stage Inference
Author-email: Hongtao Hao and Joseph Austerweil <hongtaoh@cs.wisc.edu>
Project-URL: Homepage, https://github.com/hongtaoh/bebms
Classifier: Programming Language :: Python :: 3
Classifier: License :: OSI Approved :: MIT License
Classifier: Operating System :: OS Independent
Requires-Python: >=3.7
License-File: LICENSE
Requires-Dist: pandas
Requires-Dist: numpy
Requires-Dist: scipy
Requires-Dist: matplotlib
Requires-Dist: seaborn
Requires-Dist: scikit-learn
Requires-Dist: numba
Requires-Dist: pyyaml
